flask_suspense/__init__.py
flask_suspense-0.3.0.dist-info/WHEEL
flask_suspense-0.3.0.dist-info/METADATA
flask_suspense-0.3.0.dist-info/RECORD
