Metadata-Version: 2.4
Name: flask-suspense
Version: 0.3.0
Summary: Display loaders without requiring AJAX
Author: Maxime Bouroumeau-Fuseau
Author-email: Maxime Bouroumeau-Fuseau <maxime.bouroumeau@gmail.com>
License-Expression: MIT
Requires-Dist: flask>=3.1.2
Requires-Dist: lazy-object-proxy>=1.12.0
Requires-Python: >=3.10
Project-URL: Repository, https://github.com/hyperflask/flask-suspense
